vznncv/__init__.py
vznncv/cubemx/__init__.py
vznncv/cubemx/tools/__init__.py
vznncv/cubemx/tools/_cli.py
vznncv/cubemx/tools/_cmake_generator.py
vznncv/cubemx/tools/_make_parser.py
vznncv/cubemx/tools/_project_description.py
vznncv/cubemx/tools/_project_processor.py
vznncv/cubemx/tools/_utils.py
vznncv/cubemx/tools/_version.py
vznncv/cubemx/tools/resources/templates/CmakeLists.txt
vznncv/cubemx/tools/resources/templates/build.sh
vznncv/cubemx/tools/resources/templates/openocd_stm.cfg
vznncv/cubemx/tools/resources/templates/upload-app.sh
vznncv_cubemx_tools-0.2.0.dist-info/METADATA
vznncv_cubemx_tools-0.2.0.dist-info/RECORD
vznncv_cubemx_tools-0.2.0.dist-info/WHEEL
vznncv_cubemx_tools-0.2.0.dist-info/entry_points.txt
vznncv_cubemx_tools-0.2.0.dist-info/top_level.txt
