Metadata-Version: 2.1
Name: vznncv-cubemx-tools
Version: 0.2.0
Summary: CMake project generator from STM32CubeMX project
Home-page: https://github.com/vznncv/vznncv-cubemx-tools
Author: Konstantin Kochin
License: MIT
Platform: UNKNOWN
Classifier: Programming Language :: Python :: 3.6
Classifier: License :: OSI Approved :: MIT License
Classifier: Topic :: Software Development :: Embedded Systems
Classifier: Topic :: Software Development :: Internationalization
Requires-Dist: Jinja2
Requires-Dist: click
